{"version":{"major":1,"minor":7},"type":"character","name":"Hexon","description":"","gender":"","homeworld":"","deity":"","alignment":"","quickNotes":"","languages":"","campaignNotes":"","situationalBonuses":[{"bonus":"Reduce the DC of Culture or Profession (bounty hunter) checks to recall knowledge about your mark, as well as to recall knowledge about law-enforcement individuals and practices, by 5.","source":"Theme Knowledge (Bounty Hunter)"}],"conditions":{"asleep":{"active":false,"notes":""},"bleeding":{"active":false,"notes":""},"blinded":{"active":false,"notes":""},"broken":{"active":false,"notes":""},"burning":{"active":false,"notes":""},"confused":{"active":false,"notes":""},"cowering":{"active":false,"notes":""},"dazed":{"active":false,"notes":""},"dazzled":{"active":false,"notes":""},"dead":{"active":false,"notes":""},"deafened":{"active":false,"notes":""},"dying":{"active":false,"notes":""},"encumbered":{"active":false,"notes":""},"entangled":{"active":false,"notes":""},"exhausted":{"active":false,"notes":""},"fascinated":{"active":false,"notes":""},"fatigued":{"active":false,"notes":""},"flatFooted":{"active":false,"notes":""},"frightened":{"active":false,"notes":""},"grappled":{"active":false,"notes":""},"helpless":{"active":false,"notes":""},"nauseated":{"active":false,"notes":""},"offKilter":{"active":false,"notes":""},"offTarget":{"active":false,"notes":""},"overburdened":{"active":false,"notes":""},"panicked":{"active":false,"notes":""},"paralyzed":{"active":false,"notes":""},"pinned":{"active":false,"notes":""},"prone":{"active":false,"notes":""},"shaken":{"active":false,"notes":""},"sickened":{"active":false,"notes":""},"stable":{"active":false,"notes":""},"staggered":{"active":false,"notes":""},"stunned":{"active":false,"notes":""},"unconscious":{"active":false,"notes":""}},"negativeLevels":{"permanent":0,"temporary":0},"afflictions":[],"abilityScores":{"strength":{"total":18,"base":null,"override":null,"increases":1,"pointBuy":6,"damage":0,"scoreBonuses":[],"modifierBonuses":[],"notes":""},"dexterity":{"total":14,"base":null,"override":null,"increases":1,"pointBuy":2,"damage":0,"scoreBonuses":[],"modifierBonuses":[],"notes":""},"constitution":{"total":17,"base":null,"override":null,"increases":1,"pointBuy":2,"damage":0,"scoreBonuses":[{"value":1,"type":"Theme","source":"Theme Knowledge (Bounty Hunter)"},{"value":2,"type":"Racial","source":"Shirren"}],"modifierBonuses":[],"notes":""},"intelligence":{"total":10,"base":null,"override":null,"increases":0,"pointBuy":0,"damage":0,"scoreBonuses":[],"modifierBonuses":[],"notes":""},"wisdom":{"total":14,"base":null,"override":null,"increases":1,"pointBuy":0,"damage":0,"scoreBonuses":[{"value":2,"type":"Racial","source":"Shirren"}],"modifierBonuses":[],"notes":""},"charisma":{"total":8,"base":null,"override":null,"increases":0,"pointBuy":0,"damage":0,"scoreBonuses":[{"value":-2,"type":"Racial","source":"Shirren"}],"modifierBonuses":[],"notes":""},"increases":[ ["strength","dexterity","constitution","wisdom"] ],"method":"Point Buy"},"skills":[{"total":5,"override":null,"skill":"Acrobatics","name":null,"ranks":4,"bonuses":[],"ability":"Dexterity","classSkill":true,"trainedOnly":false,"notes":""},{"total":6,"override":null,"skill":"Athletics","name":null,"ranks":3,"bonuses":[],"ability":"Strength","classSkill":true,"trainedOnly":false,"notes":""},{"total":5,"override":null,"skill":"Bluff","name":null,"ranks":6,"bonuses":[],"ability":"Charisma","classSkill":false,"trainedOnly":false,"notes":""},{"total":0,"override":null,"skill":"Computers","name":null,"ranks":0,"bonuses":[],"ability":"Intelligence","classSkill":false,"trainedOnly":true,"notes":""},{"total":2,"override":null,"skill":"Culture","name":null,"ranks":0,"bonuses":[{"value":2,"type":"Racial","source":"Cultural Fascination (Shirren)"}],"ability":"Intelligence","classSkill":false,"trainedOnly":true,"notes":""},{"total":1,"override":null,"skill":"Diplomacy","name":null,"ranks":0,"bonuses":[{"value":2,"type":"Racial","source":"Cultural Fascination (Shirren)"}],"ability":"Charisma","classSkill":false,"trainedOnly":false,"notes":""},{"total":1,"override":null,"skill":"Disguise","name":null,"ranks":2,"bonuses":[],"ability":"Charisma","classSkill":false,"trainedOnly":false,"notes":""},{"total":5,"override":null,"skill":"Engineering","name":null,"ranks":2,"bonuses":[],"ability":"Intelligence","classSkill":true,"trainedOnly":true,"notes":""},{"total":3,"override":null,"skill":"Intimidate","name":null,"ranks":1,"bonuses":[],"ability":"Charisma","classSkill":true,"trainedOnly":false,"notes":""},{"total":0,"override":null,"skill":"Life Science","name":null,"ranks":0,"bonuses":[],"ability":"Intelligence","classSkill":false,"trainedOnly":true,"notes":""},{"total":4,"override":null,"skill":"Medicine","name":null,"ranks":1,"bonuses":[],"ability":"Intelligence","classSkill":true,"trainedOnly":true,"notes":""},{"total":2,"override":null,"skill":"Mysticism","name":null,"ranks":0,"bonuses":[],"ability":"Wisdom","classSkill":false,"trainedOnly":true,"notes":""},{"total":6,"override":null,"skill":"Perception","name":null,"ranks":4,"bonuses":[],"ability":"Wisdom","classSkill":false,"trainedOnly":false,"notes":""},{"total":0,"override":null,"skill":"Physical Science","name":null,"ranks":0,"bonuses":[],"ability":"Intelligence","classSkill":false,"trainedOnly":true,"notes":""},{"total":6,"override":null,"skill":"Piloting","name":null,"ranks":1,"bonuses":[],"ability":"Dexterity","classSkill":true,"trainedOnly":false,"notes":""},{"total":2,"override":null,"skill":"Sense Motive","name":null,"ranks":0,"bonuses":[],"ability":"Wisdom","classSkill":false,"trainedOnly":false,"notes":""},{"total":-2,"override":null,"skill":"Sleight of Hand","name":null,"ranks":0,"bonuses":[],"ability":"Dexterity","classSkill":false,"trainedOnly":true,"notes":""},{"total":1,"override":null,"skill":"Stealth","name":null,"ranks":3,"bonuses":[],"ability":"Dexterity","classSkill":false,"trainedOnly":false,"notes":""},{"total":7,"override":null,"skill":"Survival","name":null,"ranks":1,"bonuses":[{"value":1,"type":"Misc","source":"Theme Knowledge (Bounty Hunter)"}],"ability":"Wisdom","classSkill":true,"trainedOnly":false,"notes":""},{"total":0,"override":null,"skill":"Profession","name":null,"ranks":0,"bonuses":[],"ability":"Intelligence","classSkill":true,"trainedOnly":true,"notes":""}],"vitals":{"temporary":0,"stamina":{"max":77,"override":null,"damage":37,"bonuses":[{"value":21,"type":"Misc","source":"Constitution"},{"value":49,"type":"Misc","source":"Soldier"},{"value":7,"type":"Misc","source":"Toughness"}],"notes":""},"health":{"max":55,"override":null,"damage":0,"bonuses":[{"value":6,"type":"Misc","source":"Shirren"},{"value":49,"type":"Misc","source":"Soldier"}],"notes":""},"resolve":{"max":7,"override":null,"damage":1,"bonuses":[{"value":3,"type":"Misc","source":"Level"},{"value":4,"type":"Misc","source":"Key Ability Score (Strength, Soldier)"}],"notes":""}},"speed":{"notes":"","land":30},"initiative":{"total":10,"bonuses":[{"value":4,"type":"Misc","source":"Improved Initiative"},{"value":4,"type":"Misc","source":"Primary Fighting Style (Blitz, Soldier)"}],"notes":""},"armorClass":{"eac":{"total":17,"override":null,"bonuses":[],"notes":""},"kac":{"total":21,"override":null,"bonuses":[{"value":1,"type":"Insight","source":"Gear Boost (Armored Advantage, Soldier)"}],"notes":""},"acVsCombatManeuver":{"total":29,"override":null,"bonuses":[],"notes":""}},"resistances":{"dr":{},"er":{"electricity":{"value":5,"sources":["+5 from Electrostatic Field, Mk 1"]}},"sr":0},"saves":{"fortitude":{"total":8,"override":null,"base":5,"bonuses":[],"ability":"Constitution","notes":""},"reflex":{"total":4,"override":null,"base":2,"bonuses":[],"ability":"Dexterity","notes":""},"will":{"total":9,"override":null,"base":5,"bonuses":[{"value":2,"type":"Misc","source":"Iron Will"}],"ability":"Wisdom","notes":""}},"attackBonuses":{"bab":{"total":7,"base":7,"notes":""},"melee":{"total":11,"override":null,"ability":"Strength","bonuses":[],"notes":""},"ranged":{"total":9,"override":null,"ability":"Dexterity","bonuses":[],"notes":""},"thrown":{"total":11,"override":null,"ability":"Strength","bonuses":[],"notes":""},"otherBonuses":[{"target":"WeaponType.Heavy Weapon","value":1,"type":"Focus","source":"Weapon Focus"}]},"race":{"name":"Shirren","description":"Once part of a ravenous hive of locust-like predators, the insectile shirrens only recently broke with their hive mind to become a race of telepaths physically addicted to their own individualism, yet dedicated to the idea of community and harmony with other races.","size":"Medium","hitPoints":6,"selectedTraits":[{"name":"Blindsense","description":"Shirrens’ sensitive antennae grant them blindsense (vibration)—the ability to sense vibrations in the air—out to 30 feet.","selectedOptions":null},{"name":"Communalism","description":"Shirrens are used to working with others as part of a team. Once per day, as long as an ally is within 10 feet, a shirren can roll a single attack roll or skill check twice and take the higher result.","selectedOptions":null},{"name":"Cultural Fascination","description":"Shirrens are eager to learn about new cultures and societies. Shirrens receive a +2 racial bonus to Culture and Diplomacy checks.","selectedOptions":null},{"name":"Limited Telepathy","description":"Shirrens can communicate telepathically with any creatures within 30 feet with whom they share a language. Conversing telepathically with multiple creatures simultaneously is just as difficult as listening to multiple people speak.","selectedOptions":null}],"abilityAdjustment":{"name":"Standard","description":"Base Ability Adjustment","adjustment":["+2 con","+2 wis","-2 cha"]},"speed":{"land":30},"reference":{"name":"Core Rulebook","shortName":"CRB","page":50}},"theme":{"name":"Bounty Hunter","bonus":"+1 con","description":"You track people down for money. It is a dangerous profession, as most of your targets understandably don’t wish to be caught. You wouldn’t have it any other way. You might have a code of ethics, never taking jobs that, say, target children or members of your own race. You might hunt down only escaped criminals. Or you might be completely amoral, taking any job that comes along — for the right price.","benefits":[{"name":"Theme Knowledge","level":1,"description":"Your mind is a cold steel trap when it comes to scraps of information about the creatures you’re tracking down. Choose a specific sentient creature that you can identify by name, alias, or specific identity to be your mark. Reduce the DC of Culture or Profession (bounty hunter) checks to recall knowledge about your mark, as well as to recall knowledge about law-enforcement individuals and practices, by 5. If you choose a mark that is known only by an alias or secret identity, this ability helps you learn facts only about the identity you know about, not any other unknown identities. Once you defeat your mark, as an action that takes 1 minute, you can study dossiers and database information about another individual to be your new mark. You can instead abandon your mark for a new one without defeating it, but if you do so, you take a –2 penalty to all skill checks for 1 week. Survival is a class skill for you, though if it is a class skill from the class you take at 1st level, you instead gain a +1 bonus to Survival checks. In addition, you gain an ability adjustment of +1 to Constitution at character creation.","selectedOptions":null},{"name":"Swift Hunter","level":6,"description":"You know just how to ask around about your marks to gain information and insight in a hurry. You can use Diplomacy to gather information about a specific individual in half the normal time, and you reduce the penalty for following tracks using Survival while moving at full speed to 0.","selectedOptions":null},{"name":"Relentless","level":12,"description":"You never seem to get tired, even when working longer and harder than everyone else in pursuit of your mark; some of your targets might even refer to you as a tireless ghost or an all-seeing hunter. You can walk or be otherwise active for 12 hours instead of 8 before needing to attempt Constitution checks for a forced march, and you can hustle for 2 hours a day during overland travel instead of 1 hour. Reduce the penalty for following tracks using Survival while moving at double speed to –10.","selectedOptions":null},{"name":"Master Hunter","level":18,"description":"Your relentless pursuit of your mark steels your determination and can renew your inner reserves of strength. Once per day while in pursuit of your mark, you can review current information about your mark for 10 minutes to regain 1 Resolve Point; this doesn’t count as resting to regain Stamina Points. Additionally, once per day when you defeat your mark, you regain 1 Resolve Point.","selectedOptions":null}],"reference":{"name":"Core Rulebook","shortName":"CRB","page":30}},"classes":[{"name":"Soldier","description":"Conflict is an inevitable result of life. On every world that harbors complex living organisms, creatures battle one another for dominance, resources, territory, or ideals. Whether you’ve taken up arms to protect others, win glory, exact revenge, or simply earn a living, you are the perfect embodiment of this truth. You’re an expert at combat of all types but tend to prefer heavy armor and weapons—the bigger, the better. You may be a career soldier, a fresh mercenary recruit, or a lone wolf who rejects authority, but whether rushing in for hand-to-hand combat or firing Tactical barrages, you’re a consummate warrior, never hesitating to put yourself in the line of fire to protect your friends.","baseHitPoints":7,"baseStaminaPoints":7,"baseSkillRanksPerLevel":4,"keyAbility":"Strength","levels":7,"spells":[],"spellsUsed":[],"spellsKnown":[0,0,0,0,0,0,0],"spellsPerDay":[0,0,0,0,0,0,0],"baseAttackBonus":7,"savingThrows":{"fortitude":5,"reflex":2,"will":5},"classSkills":["Acrobatics","Athletics","Engineering","Intimidate","Medicine","Piloting","Profession","Survival"],"features":[{"name":"Primary Fighting Style","description":"You have a preferred fighting style that represents the type of soldier you are. Each fighting style is composed of various style techniques that you learn as you gain experience. You must pick one fighting style upon taking your first soldier level, and once made, this choice cannot be changed.","options":[{"name":"Blitz","description":"The blitz fighting style is all about using speed and aggression to get into the thick of melee. You increase your speed and responsiveness, gain abilities that make you better at melee combat than your enemies, and keep on fighting even when surrounded by foes.","effects":[{"name":"Rapid Response","description":"You gain a +4 bonus to initiative checks and increase your land speed by 10 feet."},{"name":"Charge Attack","description":"As a standard action, you can make a charge without the charge penalties (see page 248), and you can substitute a bull rush for the melee attack at the end of the charge. When you gain the soldier’s onslaught class feature, you can make two attacks instead of one at the end of your charge, both with a –4 penalty."}]}]},{"name":"Primary Fighting Technique","description":"At 1st level and every 4 levels thereafter, you gain a style technique unique to your primary fighting style.","options":[]},{"name":"Heavy Weapon & Heavy Armor Proficiency","description":"Soldiers are proficient with heavy armor and heavy weapons.","options":[]},{"name":"Combat Feat","description":"At 2nd level and every 2 levels thereafter, you gain a bonus feat in addition to those gained from normal advancement. These bonus feats must be selected from those listed as combat feats. Whenever you gain a new bonus feat, you can also choose to replace one of the bonus feats you have already learned with a different bonus feat. The feat you replace can’t be one that was used as a prerequisite for another feat or other ability. You can change only one feat at any given level, and you must choose whether or not to swap the feat at the time you gain the new bonus feat.","options":[]},{"name":"Weapon Specialization","description":"You gain Weapon Specialization as a bonus feat for each weapon type this class grants you proficiency with.","options":[]},{"name":"Gear Boost","description":"At 3rd level and every 4 levels thereafter, you learn a trick called a gear boost that make you better with a particular type of weapon or armor. Choose from the gear boosts listed below. Some gear boosts require you to reach a certain soldier level to select them; this level is indicated in parentheses after the boost’s name.","options":[{"name":"Anchoring Arcana","description":"As a full action, you can make a single attack with a magic weapon against a single foe. If the attack is a ranged attack, the target must be within the first range increment. Even if the attack normally affects an area or multiple targets, it affects only your selected target. If your attack hits, you can spend 1 Resolve Point to force the target to attempt a Will saving throw (DC = 10 + half your soldier level + your key ability score modifier). If the target fails its save, it can’t voluntarily move from its current space for 1d4 rounds. This has no effect on involuntary movement, but it does prevent the creature from teleporting or moving to another plane. Once you’ve struck a foe with this attack, whether it succeeds at or fails its saving throw, it is immune to this ability for 24 hours.","effects":[]},{"name":"Armored Advantage","description":"When you are wearing armor, you gain a +1 insight bonus to your Kinetic Armor Class.","effects":[{"name":"KAC Bonus","description":"When you are wearing armor, you gain a +1 insight bonus to your Kinetic Armor Class."}]}]}],"archetype":null}],"freeArchetypes":[],"feats":{"acquiredFeats":[{"name":"Weapon Specialization","description":"You know how to get the full damage out of a weapon type your class doesn’t normally use.","prerequisite":"Character level 3rd, proficiency with selected weapon type","benefit":"Choose one weapon type (small arms, longarms, heavy weapons, etc.). You gain specialization in that weapon type, which means you add your character level to damage with the selected weapon type, or half your character level for small arms or operative melee weapons. You can never have specialization in grenades.","benefitEffect":null,"normal":null,"special":null,"isCombatFeat":true,"selectedOptions":[{"name":"Heavy Weapons","descriptions":"Add your character level to damage with heavy weapons.","effect":[{"bonus":{"value":{"property":"character.level"},"property":"character.damage.heavyWeapon","bonusType":"specialization"}}]}],"reference":{"name":"Core Rulebook","shortName":"CRB","page":163}},{"name":"Weapon Specialization","description":"You know how to get the full damage out of a weapon type your class doesn’t normally use.","prerequisite":"Character level 3rd, proficiency with selected weapon type","benefit":"Choose one weapon type (small arms, longarms, heavy weapons, etc.). You gain specialization in that weapon type, which means you add your character level to damage with the selected weapon type, or half your character level for small arms or operative melee weapons. You can never have specialization in grenades.","benefitEffect":null,"normal":null,"special":null,"isCombatFeat":true,"selectedOptions":[{"name":"Basic Melee","descriptions":"Add your character level to damage with basic melee weapons, or half your level to operative melee weapons.","effect":[{"bonus":{"value":{"property":"character.level"},"property":"character.damage.basicMelee","bonusType":"specialization"}},{"bonus":{"value":{"math":{"left":{"property":"character.level"},"operator":"div","right":{"int":2}}},"property":"character.damage.basicOperativeMelee","bonusType":"specialization"}}]}],"reference":{"name":"Core Rulebook","shortName":"CRB","page":163}},{"name":"Weapon Specialization","description":"You know how to get the full damage out of a weapon type your class doesn’t normally use.","prerequisite":"Character level 3rd, proficiency with selected weapon type","benefit":"Choose one weapon type (small arms, longarms, heavy weapons, etc.). You gain specialization in that weapon type, which means you add your character level to damage with the selected weapon type, or half your character level for small arms or operative melee weapons. You can never have specialization in grenades.","benefitEffect":null,"normal":null,"special":null,"isCombatFeat":true,"selectedOptions":[{"name":"Small Arms","descriptions":"Add half your character level to damage with small arms.","effect":[{"bonus":{"value":{"math":{"left":{"property":"character.level"},"operator":"div","right":{"int":2}}},"property":"character.damage.smallArm","bonusType":"specialization"}}]}],"reference":{"name":"Core Rulebook","shortName":"CRB","page":163}},{"name":"Weapon Specialization","description":"You know how to get the full damage out of a weapon type your class doesn’t normally use.","prerequisite":"Character level 3rd, proficiency with selected weapon type","benefit":"Choose one weapon type (small arms, longarms, heavy weapons, etc.). You gain specialization in that weapon type, which means you add your character level to damage with the selected weapon type, or half your character level for small arms or operative melee weapons. You can never have specialization in grenades.","benefitEffect":null,"normal":null,"special":null,"isCombatFeat":true,"selectedOptions":[{"name":"Advanced Melee","descriptions":"Add your character level to damage with advanced melee weapons, or half your level to operative melee weapons.","effect":[{"bonus":{"value":{"property":"character.level"},"property":"character.damage.advancedMelee","bonusType":"specialization"}},{"bonus":{"value":{"math":{"left":{"property":"character.level"},"operator":"div","right":{"int":2}}},"property":"character.damage.advancedOperativeMelee","bonusType":"specialization"}}]}],"reference":{"name":"Core Rulebook","shortName":"CRB","page":163}},{"name":"Weapon Specialization","description":"You know how to get the full damage out of a weapon type your class doesn’t normally use.","prerequisite":"Character level 3rd, proficiency with selected weapon type","benefit":"Choose one weapon type (small arms, longarms, heavy weapons, etc.). You gain specialization in that weapon type, which means you add your character level to damage with the selected weapon type, or half your character level for small arms or operative melee weapons. You can never have specialization in grenades.","benefitEffect":null,"normal":null,"special":null,"isCombatFeat":true,"selectedOptions":[{"name":"Longarms","descriptions":"Add your character level to damage with longarms.","effect":[{"bonus":{"value":{"property":"character.level"},"property":"character.damage.longarm","bonusType":"specialization"}}]}],"reference":{"name":"Core Rulebook","shortName":"CRB","page":163}},{"name":"Weapon Specialization","description":"You know how to get the full damage out of a weapon type your class doesn’t normally use.","prerequisite":"Character level 3rd, proficiency with selected weapon type","benefit":"Choose one weapon type (small arms, longarms, heavy weapons, etc.). You gain specialization in that weapon type, which means you add your character level to damage with the selected weapon type, or half your character level for small arms or operative melee weapons. You can never have specialization in grenades.","benefitEffect":null,"normal":null,"special":null,"isCombatFeat":true,"selectedOptions":[{"name":"Sniper Weapons","descriptions":"Add your character level to damage with sniper weapons.","effect":[{"bonus":{"value":{"property":"character.level"},"property":"character.damage.sniper","bonusType":"specialization"}}]}],"reference":{"name":"Core Rulebook","shortName":"CRB","page":163}},{"name":"Heavy Armor Proficiency","description":"You know how to use heavy armor.","prerequisite":"Str 13, proficiency in light armor.","benefit":"You gain proficiency in heavy armor.","benefitEffect":[{"append":{"value":{"armorType":"heavy"},"property":"character.proficiency.armor"}}],"normal":null,"special":null,"isCombatFeat":true,"selectedOptions":null,"reference":{"name":"Core Rulebook","shortName":"CRB","page":158}},{"name":"Heavy Weapon Proficiency","description":"You know how to use heavy weapons.","prerequisite":"Str 13, proficiency in small arms and longarms.","benefit":"You gain proficiency in heavy weapons.","benefitEffect":[{"append":{"value":{"weaponType":"heavyWeapon"},"property":"character.proficiency.weapon"}}],"normal":null,"special":null,"isCombatFeat":true,"selectedOptions":null,"reference":{"name":"Core Rulebook","shortName":"CRB","page":158}},{"name":"Shield Proficiency","description":"You are trained in the use of shields.","prerequisite":null,"benefit":"You gain proficiency with shields.","benefitEffect":[{"append":{"value":{"armorType":"shield"},"property":"character.proficiency.armor"}}],"normal":null,"special":"Mechanics with an exocortex, solarians, soldiers, and vanguards gain proficiency with shields automatically at 1st level.","isCombatFeat":true,"selectedOptions":null,"reference":{"name":"Character Operations Manual","shortName":"COM","page":118}},{"name":"Advanced Melee Weapon Proficiency","description":"You know how to use advanced melee weapons.","prerequisite":"Proficiency in basic melee weapons.","benefit":"You gain proficiency in advanced melee weapons (see Weapon Proficiency on page 243).","benefitEffect":[{"append":{"value":{"weaponType":"advancedMelee"},"property":"character.proficiency.weapon"}}],"normal":null,"special":null,"isCombatFeat":true,"selectedOptions":null,"reference":{"name":"Core Rulebook","shortName":"CRB","page":154}},{"name":"Weapon Specialization","description":"You know how to get the full damage out of a weapon type your class doesn’t normally use.","prerequisite":"Character level 3rd, proficiency with selected weapon type","benefit":"Choose one weapon type (small arms, longarms, heavy weapons, etc.). You gain specialization in that weapon type, which means you add your character level to damage with the selected weapon type, or half your character level for small arms or operative melee weapons. You can never have specialization in grenades.","benefitEffect":null,"normal":null,"special":null,"isCombatFeat":true,"selectedOptions":[{"name":"Sniper Weapons","descriptions":"Add your character level to damage with sniper weapons.","effect":[{"bonus":{"value":{"property":"character.level"},"property":"character.damage.sniper","bonusType":"specialization"}}]}],"reference":{"name":"Core Rulebook","shortName":"CRB","page":163}},{"name":"Improved Initiative","description":"Your quick reflexes allow you to react rapidly to danger.","prerequisite":null,"benefit":"You gain a +4 bonus to initiative checks.","benefitEffect":[{"bonus":{"value":{"int":4},"property":"character.initiative","bonusType":"misc"}}],"normal":null,"special":null,"isCombatFeat":true,"selectedOptions":null,"reference":{"name":"Core Rulebook","shortName":"CRB","page":158}},{"name":"Weapon Focus","description":"You have increased training in a particular weapon type, making it easier to hit your target.","prerequisite":"Proficiency with selected weapon type","benefit":"Chose one weapon type (small arms, longarms, heavy weapons, etc.). You gain a +1 bonus to attack rolls with that weapon type. If your base attack bonus is at least 3 lower than your character level (or your mechanic’s class level, if you are a drone), you gain a +2 bonus instead.","benefitEffect":null,"normal":null,"special":null,"isCombatFeat":true,"selectedOptions":[{"name":"Heavy Weapons","descriptions":"You gain a +1 bonus to attack rolls with heavy weapons. If your base attack bonus is at least 3 lower than your character level, you gain a +2 bonus instead.","effect":[]}],"reference":{"name":"Core Rulebook","shortName":"CRB","page":163}},{"name":"Diversion","description":"You can draw attention to yourself, allowing your allies to slip away.","prerequisite":null,"benefit":"When you successfully use Bluff to create a distraction, you can allow an ally to attempt a Stealth check to hide (instead of attempting to hide yourself). You can attempt to allow multiple allies to use Stealth to hide, but you take a –5 penalty to your Bluff check for every ally after the first, and on a failed check no ally can attempt to hide.","benefitEffect":null,"normal":"Using Bluff to create a distraction allows only you to attempt a Stealth check to hide.","special":null,"isCombatFeat":false,"selectedOptions":null,"reference":{"name":"Core Rulebook","shortName":"CRB","page":156}},{"name":"Toughness","description":"You have enhanced physical resilience, and harsh conditions or long exertions don’t easily tire you.","prerequisite":null,"benefit":"For every character level you have (and whenever you gain a new level), you gain 1 Stamina Point. In addition, you gain a +4 bonus to Constitution checks to continue running, to avoid damage from a forced march, to hold your breath, and to avoid damage from starvation or thirst. You also gain a +4 bonus to Fortitude saving throws to avoid taking damage from hot or cold environments, to withstand the harmful effects of thick and thin atmospheres, to avoid choking when breathing in heavy smoke, and to avoid fatigue caused by sleep deprivation.","benefitEffect":[{"bonus":{"value":{"property":"character.level"},"property":"character.stamina","bonusType":"misc"}}],"normal":null,"special":null,"isCombatFeat":false,"selectedOptions":null,"reference":{"name":"Core Rulebook","shortName":"CRB","page":163}},{"name":"Iron Will","description":"You are more resistant to mental effects.","prerequisite":null,"benefit":"You gain a +2 bonus to Will saving throws.","benefitEffect":[{"bonus":{"value":{"int":2},"property":"character.will","bonusType":"misc"}}],"normal":null,"special":null,"isCombatFeat":false,"selectedOptions":null,"reference":{"name":"Core Rulebook","shortName":"CRB","page":158}}],"notes":""},"inventory":[{"type":"Ammunition","id":"608730446","name":"Battery, Super-Capacity","description":"Batteries charge powered weapons, but they can also be used to power an array of items, including powered armor and technological items. Batteries have a standardized size and weight, and items that take batteries all have a slot into which they fit, regardless of the item’s actual size. Weapons that use batteries list the highest-capacity battery they are capable of using as well as how many charges from the battery that each shot consumes.","level":4,"price":390,"bulk":0,"special":null,"capacity":80,"ammunitionType":"Charge","reference":{"name":"Core Rulebook","shortName":"CRB","page":179},"used":0,"stashed":false,"notes":"","quantity":1,"tags":[]},{"type":"Armor","id":"821111173","isEquipped":true,"stashed":false,"upgradeIds":["1957550740"],"notes":"","quantity":1,"tags":[],"name":"Battle Harness","description":"The battle harness is the basic powered armor frame used by infantry units in professional militaries.","level":5,"price":3450,"bulk":20,"eacBonus":9,"kacBonus":12,"maxDexBonus":2,"speed":{"land":30},"strength":18,"unarmedDamage":{"dice":{"count":1,"sides":10},"damage":["B"],"alternateDamage":null},"size":"Medium","capacity":20,"usage":"1/hour","weaponSlots":1,"reach":5,"armorCheckPenalty":-4,"upgradeSlots":1,"armorType":"Powered","reference":{"name":"Core Rulebook","shortName":"CRB","page":204}},{"type":"Weapon","id":"41573946","name":"Doshko, Tactical","description":"The traditional weapon of the vesk, the doshko is composed of one to four triangular blades arranged in a row and attached to a long haft. Ideal for devastating overhand blows and catching and parrying enemy weapons, its use is a highly respected art form in traditional vesk society, but it also sees use by creatures of other races as a variant axe. Traditionally, doshkos are made of steel, but in recent decades they have been crafted using advanced metallurgic techniques and even quantum technology to improve the stabbing edges.","level":1,"price":240,"bulk":1,"weaponType":"Advanced Melee","handedness":2,"category":null,"toHit":11,"damage":{"dice":{"count":1,"sides":12},"damage":["P"],"alternateDamage":[]},"damageBonus":11,"critical":null,"special":[{"name":"Analog","additionalInfo":null},{"name":"Unwieldy","additionalInfo":null}],"range":null,"capacity":null,"ammunitionType":null,"ammunitionId":null,"usage":null,"accessoryIds":[],"fusionIds":[],"reference":{"name":"Core Rulebook","shortName":"CRB","page":172},"isEquipped":false,"stashed":false,"proficient":true,"specialization":true,"notes":"","quantity":1,"tags":[]},{"type":"ArmorUpgrade","id":"1957550740","name":"Electrostatic Field, Mk 1","description":"This field over your armor grants you electricity resistance 5, and any creature that touches you or deals damage to you with a melee weapon takes 1d6 electricity damage.","level":5,"price":3000,"bulk":0,"capacity":null,"usage":null,"slots":1,"forArmorTypes":["Light","Heavy","Powered","Shield"],"itemType":"Technological","ammunitionId":null,"stashed":false,"isInstalled":false,"notes":"","reference":{"name":"Core Rulebook","shortName":"CRB","page":205},"quantity":1,"tags":[]},{"type":"Weapon","id":"510191995","name":"Meteor Glaive, Tactical","description":"The glaive is an ancient weapon, originally developed for use by and against mounted warriors. The meteor glaive is the Skyfire Legion's update on the original design, incorporating a petrol tank near the base of the slightly curved blade and relying on a long shaft to keep the wielder at a safe distance. Meteor glaives are classified into tactical, advanced, elite, and paragon models.","level":6,"price":4390,"bulk":2,"weaponType":"Advanced Melee","handedness":2,"category":"Flame","toHit":11,"damage":{"dice":{"count":1,"sides":12},"damage":["F","S"],"alternateDamage":null},"damageBonus":11,"critical":{"name":"Wound","additionalInfo":null},"special":[{"name":"Fueled","additionalInfo":"(capacity 40; usage 4)"},{"name":"Reach","additionalInfo":null}],"range":null,"capacity":40,"ammunitionType":null,"ammunitionId":"608730446","usage":4,"accessoryIds":[],"fusionIds":[],"reference":{"name":"Armory","shortName":"ARM","page":38},"isEquipped":true,"stashed":false,"proficient":true,"specialization":true,"notes":"","quantity":1,"tags":[]},{"type":"Weapon","id":"2002839823","name":"Plasma Guide, Series-28","description":"A plasma guide maintains a magnetic guidance system around its plasma discharge, which continues guiding the shot after it is fired. This increases accuracy at ranges far beyond those of typical plasma weapons and bypasses the advantage of partial cover as the magnetic guidance directs the plasma toward its target. Vesk snipers are believed to be the earliest users of the plasma guide during the Silent War, but it's become a standard in many military and mercenary arsenals since then. This weapon has been continually refined since its invention; series-21series-28, series-37, series-42, series-62, and series-73 plasma guides have proven generally stable and thus remain in production.","level":6,"price":4920,"bulk":2,"weaponType":"Sniper","handedness":2,"category":"Plasma","toHit":9,"damage":{"dice":{"count":1,"sides":10},"damage":["E","F"],"alternateDamage":[]},"damageBonus":7,"critical":{"name":"Wound","additionalInfo":null},"special":[{"name":"Guided","additionalInfo":null},{"name":"Sniper","additionalInfo":"(250 ft.)"},{"name":"Unwieldy","additionalInfo":null}],"range":60,"capacity":40,"ammunitionType":"Charges","ammunitionId":null,"usage":5,"accessoryIds":[],"fusionIds":[],"reference":{"name":"Armory","shortName":"ARM","page":43},"isEquipped":true,"stashed":false,"proficient":true,"specialization":true,"notes":"","quantity":1,"tags":[]},{"type":"Ammunition","id":"1881207681","name":"Rounds, Heavy","description":"Cased rounds are housed in magazines, which can be fitted into the appropriate weapon.","level":2,"price":90,"bulk":0.1,"special":null,"capacity":20,"ammunitionType":"Round","reference":{"name":"Core Rulebook","shortName":"CRB","page":179},"used":2,"stashed":false,"notes":"","quantity":1,"tags":[]},{"type":"Ammunition","id":"1899803941","name":"Rounds, Heavy","description":"Cased rounds are housed in magazines, which can be fitted into the appropriate weapon.","level":2,"price":90,"bulk":0.1,"special":null,"capacity":20,"ammunitionType":"Round","reference":{"name":"Core Rulebook","shortName":"CRB","page":179},"used":0,"stashed":false,"notes":"","quantity":2,"tags":[]},{"type":"Weapon","id":"Unarmed Strike","name":"Unarmed Strike","description":"An unarmed strike can be dealt with any limb or appendage. Unarmed strikes deal nonlethal damage, and the damage from an unarmed strike is considered weapon damage for the purposes of effects that give you a bonus to weapon damage rolls.","level":7,"price":0,"bulk":0,"weaponType":"Basic Melee","handedness":1,"category":null,"toHit":11,"damage":{"dice":{"count":1,"sides":10},"damage":["B"],"alternateDamage":null},"damageBonus":11,"critical":null,"special":[{"name":"Archaic","additionalInfo":null},{"name":"Nonlethal","additionalInfo":null}],"range":null,"capacity":null,"ammunitionType":null,"ammunitionId":null,"usage":null,"accessoryIds":[],"fusionIds":[],"reference":{"name":"Core Rulebook","shortName":"CRB","page":171},"isEquipped":true,"stashed":false,"proficient":true,"specialization":true,"notes":"","quantity":1,"tags":[]},{"type":"Weapon","id":"508172827","name":"X-Gen Gun, Tactical","description":"X-gen guns are named for their external generator'a power pack that drives the automatic feed of the weapon. They are common on fortified bases and in large armed encampments.","level":6,"price":4240,"bulk":2,"weaponType":"Heavy Weapon","handedness":2,"category":"Projectile","toHit":10,"damage":{"dice":{"count":1,"sides":12},"damage":["P"],"alternateDamage":[]},"damageBonus":7,"critical":null,"special":[{"name":"Automatic","additionalInfo":null}],"range":120,"capacity":80,"ammunitionType":"Rounds","ammunitionId":"1881207681,1899803941,2120504570","usage":2,"accessoryIds":[],"fusionIds":[],"reference":{"name":"Core Rulebook","shortName":"CRB","page":177},"isEquipped":false,"stashed":false,"proficient":true,"specialization":true,"notes":"","quantity":1,"tags":[]}],"bulk":{"current":{"total":7,"override":null,"notes":""},"encumbered":{"limit":9},"overburdened":{"limit":18,"override":null,"notes":""}},"credits":10435,"upbs":0,"senses":[{"senseType":"Blindsense","additionalInfo":"vibration","range":30},{"senseType":"Limited Telepathy","additionalInfo":null,"range":30}],"counters":[],"additionalSpells":[],"drone":null}